.gitattributes
.gitignore
.pre-commit-config.yaml
.travis.yml
LICENSE.md
MANIFEST.in
README.md
requirements.txt
setup.cfg
setup.py
versioneer.py
archapp/__init__.py
archapp/_version.py
archapp/config.py
archapp/data.py
archapp/dates.py
archapp/doc_sub.py
archapp/epics.py
archapp/file_formats.py
archapp/interactive.py
archapp/mgmt.py
archapp/print_formats.py
archapp/url.py
archapp.egg-info/PKG-INFO
archapp.egg-info/SOURCES.txt
archapp.egg-info/dependency_links.txt
archapp.egg-info/requires.txt
archapp.egg-info/top_level.txt
archapp/tests/__init__.py
archapp/tests/test_data.py
archapp/tests/test_dates.py
archapp/tests/test_doc_sub.py
archapp/tests/test_mgmt.py
archapp/tests/test_print_formats.py
archapp/tests/test_url.py
bin/arch_app
bin/arch_env
bin/command_line.py
bin/misc/pvlist.txt
bin/misc/short.txt
bin/misc/vac_csv
bin/misc/vac_csv.py
conda-recipe/build.sh
conda-recipe/meta.yaml
docs/Makefile
docs/make.bat
docs/source/bash.rst
docs/source/conf.py
docs/source/data.rst
docs/source/index.rst
docs/source/ipython.rst
docs/source/mgmt.rst
docs/source/utils.rst