Metadata-Version: 2.1
Name: archapp
Version: 1.1.0
Summary: Archiver Appliance Python Interface
Home-page: UNKNOWN
Author: Zachary Lentz
Author-email: zlentz@slac.stanford.edu
License: BSD
Platform: UNKNOWN
Requires-Python: >=3.6
License-File: LICENSE.md
